mysql_batch/__init__.py
mysql_batch/__main__.py
mysql_batch/mysql_batch.py
mysql_batch-1.2.1.dist-info/LICENSE
mysql_batch-1.2.1.dist-info/METADATA
mysql_batch-1.2.1.dist-info/WHEEL
mysql_batch-1.2.1.dist-info/entry_points.txt
mysql_batch-1.2.1.dist-info/top_level.txt
mysql_batch-1.2.1.dist-info/RECORD
